rt_congestion_control/__init__.py
rt_congestion_control/admm.py
rt_congestion_control/agent.py
rt_congestion_control/communication.py
rt_congestion_control/memory.py
rt_congestion_control/so.py
RT_Congestion_Control-1.3.dist-info/LICENSE.txt
RT_Congestion_Control-1.3.dist-info/METADATA
RT_Congestion_Control-1.3.dist-info/WHEEL
RT_Congestion_Control-1.3.dist-info/top_level.txt
RT_Congestion_Control-1.3.dist-info/RECORD
