Metadata-Version: 2.1
Name: RT-Congestion-Control
Version: 1.3
Summary: Implement exogenous peer to peer algorithm for Real time Congestion Control in distribution networks
Home-page: https://gitlab.com/satie.sete/rt-congestion-control
Author: Guénolé CHEROT
Author-email: guenole.cherot@ens-rennes.fr
License: MIT
Download-URL: https://gitlab.com/satie.sete/rt-congestion-control/-/archive/1.3/admm-1.3.tar.gz
Keywords: Distributed Optimisation,Peer-to-peer,Distribution System Operator,Cost Allocation,Real-Time,Flexibility,Congestion Management
Platform: UNKNOWN
Requires-Dist: pandapower
Requires-Dist: flake8
Requires-Dist: matplotlib
Requires-Dist: osqp
Requires-Dist: tqdm
Requires-Dist: numpy
Requires-Dist: scipy
Requires-Dist: joblib
Requires-Dist: numba
Requires-Dist: plotly
